ailice/AIliceMain.py
ailice/AIliceTurbo.py
ailice/AServices.py
ailice/__init__.py
ailice/common/AConfig.py
ailice/common/ADataType.py
ailice/common/AExceptions.py
ailice/common/AGas.py
ailice/common/AMessenger.py
ailice/common/APrompts.py
ailice/common/ARemoteAccessors.py
ailice/common/ASerialization.py
ailice/common/__init__.py
ailice/common/lightRPC.py
ailice/common/utils/AFileUtils.py
ailice/common/utils/ALogger.py
ailice/common/utils/ATextSpliter.py
ailice/common/utils/__init__.py
ailice/core/AConversation.py
ailice/core/AInterpreter.py
ailice/core/AProcessor.py
ailice/core/__init__.py
ailice/core/llm/AFormatter.py
ailice/core/llm/ALLMPool.py
ailice/core/llm/AModelAnthropic.py
ailice/core/llm/AModelCausalLM.py
ailice/core/llm/AModelChatGPT.py
ailice/core/llm/AModelMistral.py
ailice/core/llm/ATokenEstimator.py
ailice/core/llm/__init__.py
ailice/modules/AArxiv.py
ailice/modules/ABrowser.py
ailice/modules/AComputer.py
ailice/modules/ADuckDuckGo.py
ailice/modules/AFileBrowser.py
ailice/modules/AGoogle.py
ailice/modules/AGoogleAPI.py
ailice/modules/AMCPWrapper.py
ailice/modules/APDFBrowser.py
ailice/modules/AScripter.py
ailice/modules/AScrollablePage.py
ailice/modules/ASpeech.py
ailice/modules/AStorageVecDB.py
ailice/modules/AStorageVecDBHF.py
ailice/modules/AStorageWeaviate.py
ailice/modules/ATextBrowser.py
ailice/modules/AWebBrowser.py
ailice/modules/AWebBrowserPlaywright.py
ailice/modules/__init__.py
ailice/modules/speech/AAudioSource.py
ailice/modules/speech/ASTT_Whisper.py
ailice/modules/speech/ATTS_ChatTTS.py
ailice/modules/speech/ATTS_LJS.py
ailice/modules/speech/__init__.py
ailice/prompts/APromptChat.py
ailice/prompts/APromptCoder.py
ailice/prompts/APromptCoderProxy.py
ailice/prompts/APromptDocReader.py
ailice/prompts/APromptMain.py
ailice/prompts/APromptModuleCoder.py
ailice/prompts/APromptResearcher.py
ailice/prompts/APromptSearchEngine.py
ailice/prompts/ARegex.py
ailice/prompts/ATools.py
ailice/prompts/__init__.py
mseep_ailice-0.4.0.dist-info/licenses/LICENSE
mseep_ailice-0.4.0.dist-info/METADATA
mseep_ailice-0.4.0.dist-info/WHEEL
mseep_ailice-0.4.0.dist-info/top_level.txt
mseep_ailice-0.4.0.dist-info/RECORD
